hcl_processor/__init__.py
hcl_processor/bedrock_client.py
hcl_processor/cli.py
hcl_processor/config/system_config.py
hcl_processor/config_loader.py
hcl_processor/file_processor.py
hcl_processor/llm_provider.py
hcl_processor/logger_config.py
hcl_processor/main.py
hcl_processor/output_writer.py
hcl_processor/provider_factory.py
hcl_processor/utils.py
hcl_processor-0.15.0rc0.dist-info/METADATA
hcl_processor-0.15.0rc0.dist-info/WHEEL
hcl_processor-0.15.0rc0.dist-info/entry_points.txt
hcl_processor-0.15.0rc0.dist-info/RECORD
