Metadata-Version: 2.4
Name: hcl-processor
Version: 0.15.0rc0
Summary: A tool for analyzing HCL files.
Author: S-mishina
Author-email: 45090872+S-mishina@users.noreply.github.com
Requires-Python: >=3.10,<4.0
Classifier: Programming Language :: Python :: 3
Classifier: Programming Language :: Python :: 3.10
Classifier: Programming Language :: Python :: 3.11
Classifier: Programming Language :: Python :: 3.12
Classifier: Programming Language :: Python :: 3.13
Classifier: Programming Language :: Python :: 3.14
Requires-Dist: Cerberus (==1.3.8)
Requires-Dist: Jinja2 (==3.1.6)
Requires-Dist: PyYAML (==6.0.3)
Requires-Dist: attrs (==25.4.0)
Requires-Dist: boto3 (==1.42.21)
Requires-Dist: botocore (==1.42.21)
Requires-Dist: jmespath (==1.0.1)
Requires-Dist: jsonschema (==4.25.1)
Requires-Dist: jsonschema-specifications (==2025.9.1)
Requires-Dist: lark (==1.3.1)
Requires-Dist: prettytable (==3.17.0)
Requires-Dist: python-dateutil (==2.9.0.post0)
Requires-Dist: python-hcl2 (==7.3.1)
Requires-Dist: pytz (==2025.2)
Requires-Dist: referencing (==0.37.0)
Requires-Dist: rpds-py (==0.30.0)
Requires-Dist: s3transfer (==0.16.0)
Requires-Dist: six (==1.17.0)
Requires-Dist: tabulate (==0.9.0)
Requires-Dist: tomli (==2.3.0)
Requires-Dist: tzdata (==2025.3)
Requires-Dist: wcwidth (==0.2.14)
